igem/__init__.py
igem/analyze/__init__.py
igem/analyze/analyze.py
igem/analyze/interaction.py
igem/core/__init__.py
igem/core/mixins/__init__.py
igem/core/mixins/get_data_mixin.py
igem/core/settings_manager.py
igem/db/__init__.py
igem/db/base.py
igem/db/create_db_mixin.py
igem/db/database.py
igem/db/models/__init__.py
igem/db/models/config_models.py
igem/db/models/etl_models.py
igem/db/models/ge_models.py
igem/db/seed/initial_config.json
igem/db/seed/initial_data_sources.json
igem/describe/__init__.py
igem/describe/describe.py
igem/etl/__init__.py
igem/etl/dtps/__init__.py
igem/etl/dtps/dtp_dbsnp.py
igem/etl/dtps/dtp_hgnc.py
igem/etl/dtps/dtp_reactome.py
igem/etl/dtps/worker_dbsnp.py
igem/etl/etl_manager.py
igem/etl/mixins/__init__.py
igem/etl/mixins/base_dtp.py
igem/etl/mixins/entity_query_mixin.py
igem/etl/mixins/gene_query_mixin.py
igem/etl/mixins/variant_query_mixin.py
igem/igem.py
igem/load/__init__.py
igem/load/load.py
igem/load/load_plink.py
igem/modify/__init__.py
igem/modify/modify.py
igem/plot/__init__.py
igem/plot/plot.py
igem/survey/__init__.py
igem/survey/survey.py
igem/utils/__init__.py
igem/utils/db_loader.py
igem/utils/file_hash.py
igem/utils/formatter.py
igem/utils/logger.py
igem-2.0.0.dist-info/METADATA
igem-2.0.0.dist-info/WHEEL
igem-2.0.0.dist-info/RECORD
