Metadata-Version: 2.1
Name: igem
Version: 2.0.0
Summary: 
Home-page: https://github.com/HallLab/IGEM
License: BSD-3-Clause
Author: Andre Rico
Author-email: andreluis.rico@pennmedicine.upenn.edu
Requires-Python: >=3.10,<3.13
Classifier: Development Status :: 4 - Beta
Classifier: Intended Audience :: Science/Research
Classifier: License :: OSI Approved :: BSD License
Classifier: Programming Language :: Python :: 3
Classifier: Programming Language :: Python :: 3.10
Classifier: Programming Language :: Python :: 3.11
Classifier: Programming Language :: Python :: 3.12
Classifier: Topic :: Scientific/Engineering :: Bio-Informatics
Requires-Dist: clarite (>=2.4.1,<3.0.0)
Requires-Dist: colorama (>=0.4.6,<0.5.0)
Requires-Dist: pandas (>=2.2,<3.0)
Requires-Dist: pandas-plink (>=2.3.2,<3.0.0)
Requires-Dist: sqlalchemy (>=2.0.41,<3.0.0)
Project-URL: Documentation, https://igem.readthedocs.io/en/latest/
Project-URL: Repository, https://github.com/HallLab/IGEM
